vk_wallet_api/__init__.py
vk_wallet_api/schemes.py
vk_wallet_api/wallet.py
vk_wallet_api-1.0.1.dist-info/METADATA
vk_wallet_api-1.0.1.dist-info/WHEEL
vk_wallet_api-1.0.1.dist-info/top_level.txt
vk_wallet_api-1.0.1.dist-info/RECORD
